pyisy/__init__.py
pyisy/__main__.py
pyisy/clock.py
pyisy/configuration.py
pyisy/connection.py
pyisy/constants.py
pyisy/exceptions.py
pyisy/helpers.py
pyisy/isy.py
pyisy/logging.py
pyisy/networking.py
pyisy/node_servers.py
pyisy/events/__init__.py
pyisy/events/eventreader.py
pyisy/events/strings.py
pyisy/events/tcpsocket.py
pyisy/events/websocket.py
pyisy/nodes/__init__.py
pyisy/nodes/group.py
pyisy/nodes/node.py
pyisy/nodes/nodebase.py
pyisy/programs/__init__.py
pyisy/programs/folder.py
pyisy/programs/program.py
pyisy/variables/__init__.py
pyisy/variables/variable.py
pyisy-3.4.1.dist-info/licenses/LICENSE.txt
pyisy-3.4.1.dist-info/METADATA
pyisy-3.4.1.dist-info/WHEEL
pyisy-3.4.1.dist-info/top_level.txt
pyisy-3.4.1.dist-info/RECORD
