Metadata-Version: 2.4
Name: pyisy
Version: 3.4.1
Summary: Python module to talk to ISY devices from UDI.
Home-page: https://github.com/automicus/PyISY
Author: Ryan Kraus
Author-email: Ryan Kraus <automicus@gmail.com>, shbatm <support@shbatm.com>
License: Apache-2.0
Project-URL: Source Code, https://github.com/automicus/PyISY
Project-URL: Homepage, https://github.com/automicus/PyISY
Keywords: home,automation,isy,isy994,isy-994,UDI,polisy,eisy
Platform: any
Classifier: Development Status :: 5 - Production/Stable
Classifier: Intended Audience :: End Users/Desktop
Classifier: Intended Audience :: Developers
Classifier: License :: OSI Approved :: Apache Software License
Classifier: Operating System :: OS Independent
Classifier: Programming Language :: Python
Classifier: Programming Language :: Python :: 3
Classifier: Topic :: Home Automation
Requires-Python: >=3.9
License-File: LICENSE.txt
Requires-Dist: aiohttp>=3.8.1
Requires-Dist: python-dateutil>=2.8.1
Requires-Dist: requests>=2.28.1
Requires-Dist: colorlog>=6.6.0
Dynamic: author
Dynamic: home-page
Dynamic: license-file
Dynamic: platform
